{"navindia_code": "38964", "scheme_name": "LIC MF Dividend Yield Fund - Regular (G)", "amc": "LIC Mutual Fund", "sebi_category": "Dividend Yield Fund", "benchmark": "NIFTY 500", "n_months": 89, "years": 7.4, "gappy": false, "is_thematic": false, "is_hybrid": false, "excess_cagr": 0.0534, "cagr_paper": 0.201, "cagr_bench": 0.1476, "info_ratio": 0.7796, "t_stat": 2.1231, "years_needed": 6.3206, "tracking_error": 0.0572, "ic_mean": -0.0039, "ic_t": -0.2143, "sizing_edge_cum": -0.3245, "hit_rate_monthly": 0.5843, "mag_hit": 0.6442, "slugging": 1.29, "avg_win": 0.01421, "avg_loss": -0.01102, "port_hit_cnt": 0.4872, "port_hit_aum": 0.4842, "port_slug_cnt": 0.0435, "port_slug_aum": 0.0414, "herfindahl": 0.0216, "herfindahl_avg": 0.0318, "eff_n": 46.3, "avg_names": 46.1, "boot_meanA_lo": 0.00017, "boot_meanA_hi": 0.00743, "boot_p_positive": 0.9795, "verdict": "skilled", "verdict_why": "+5.3%/yr gross, t=2.1, bootstrap 98% (mixed-source)", "basis": "GROSS holdings-implied total-return excess vs the SEBI-category benchmark (pre-cost, pre-cash-drag, pre-factor-deflation); domestic equity sleeve only, month-end snapshots. ‘Holding-rank IC’ is a cap-tilt-contaminated proxy, not pure active-weight selection (needs point-in-time benchmark weights).", "ts": [{"ym": "2019-01", "A": 0.00204, "rp": -0.00205, "rb": -0.00409, "ic": 0.2485, "n": 10, "herf": 0.11373, "sz": 0.00301, "hc": 0.4, "ha": 0.4087, "sc": 0.3, "sa2": 0.3247}, {"ym": "2019-02", "A": -0.02833, "rp": 0.05145, "rb": 0.07978, "ic": 0.0243, "n": 10, "herf": 0.11427, "sz": 0.00555, "hc": 0.2, "ha": 0.2213, "sc": -0.3, "sa2": -0.3168}, {"ym": "2019-03", "A": 0.00537, "rp": 0.0055, "rb": 0.00012, "ic": 0.2047, "n": 20, "herf": 0.06459, "sz": 0.00588, "hc": 0.5, "ha": 0.5653, "sc": 0.15, "sa2": 0.1951}, {"ym": "2019-04", "A": -0.01882, "rp": -0.00318, "rb": 0.01564, "ic": -0.2662, "n": 36, "herf": 0.03688, "sz": -0.0098, "hc": 0.3889, "ha": 0.3108, "sc": 0.0278, "sa2": -0.0523}, {"ym": "2019-05", "A": 0.00583, "rp": -0.00735, "rb": -0.01317, "ic": 0.1053, "n": 36, "herf": 0.03668, "sz": 0.00404, "hc": 0.5, "ha": 0.5695, "sc": 0.3333, "sa2": 0.3824}, {"ym": "2019-06", "A": 0.00851, "rp": -0.05238, "rb": -0.06089, "ic": -0.0381, "n": 36, "herf": 0.03695, "sz": 0.00397, "hc": 0.5556, "ha": 0.5904, "sc": 0.5, "sa2": 0.555}, {"ym": "2019-07", "A": 0.02618, "rp": 0.0208, "rb": -0.00538, "ic": -0.1077, "n": 38, "herf": 0.0334, "sz": -0.00233, "hc": 0.6579, "ha": 0.6535, "sc": 0.3684, "sa2": 0.3256}, {"ym": "2019-08", "A": 0.00917, "rp": 0.04991, "rb": 0.04074, "ic": -0.3324, "n": 51, "herf": 0.02425, "sz": -0.0153, "hc": 0.5686, "ha": 0.4768, "sc": 0.0392, "sa2": -0.0347}, {"ym": "2019-09", "A": 0.00735, "rp": 0.04606, "rb": 0.03872, "ic": 0.0544, "n": 51, "herf": 0.02419, "sz": -0.00561, "hc": 0.6078, "ha": 0.606, "sc": 0.3333, "sa2": 0.2993}, {"ym": "2019-10", "A": -0.01623, "rp": -0.00312, "rb": 0.01311, "ic": -0.0211, "n": 49, "herf": 0.02431, "sz": 0.00091, "hc": 0.4082, "ha": 0.4287, "sc": 0.0816, "sa2": 0.0603}, {"ym": "2019-11", "A": -0.00311, "rp": 0.00296, "rb": 0.00608, "ic": 0.1468, "n": 50, "herf": 0.02425, "sz": 0.00289, "hc": 0.4, "ha": 0.4505, "sc": 0.02, "sa2": 0.023}, {"ym": "2019-12", "A": 0.02975, "rp": 0.02875, "rb": -0.00099, "ic": -0.1941, "n": 50, "herf": 0.02448, "sz": -0.00479, "hc": 0.66, "ha": 0.5926, "sc": -0.08, "sa2": -0.1361}, {"ym": "2020-01", "A": 0.02258, "rp": -0.04019, "rb": -0.06277, "ic": 0.3044, "n": 49, "herf": 0.02343, "sz": 0.01148, "hc": 0.5918, "ha": 0.6474, "sc": 0.2857, "sa2": 0.3239}, {"ym": "2020-02", "A": 0.05273, "rp": -0.18762, "rb": -0.24035, "ic": 0.2415, "n": 47, "herf": 0.02514, "sz": 0.02113, "hc": 0.617, "ha": 0.6825, "sc": 0.4894, "sa2": 0.5907}, {"ym": "2020-03", "A": -0.02183, "rp": 0.12351, "rb": 0.14535, "ic": -0.0926, "n": 47, "herf": 0.02692, "sz": -0.00567, "hc": 0.4255, "ha": 0.4403, "sc": -0.2766, "sa2": -0.2646}, {"ym": "2020-04", "A": 0.01719, "rp": -0.00591, "rb": -0.0231, "ic": -0.0007, "n": 47, "herf": 0.02802, "sz": -0.00136, "hc": 0.5106, "ha": 0.5225, "sc": 0.2128, "sa2": 0.2117}, {"ym": "2020-05", "A": -0.0169, "rp": 0.06704, "rb": 0.08394, "ic": -0.2325, "n": 43, "herf": 0.02971, "sz": -0.01556, "hc": 0.3721, "ha": 0.3325, "sc": -0.5116, "sa2": -0.5156}, {"ym": "2020-06", "A": 0.01617, "rp": 0.08433, "rb": 0.06816, "ic": 0.0524, "n": 43, "herf": 0.02946, "sz": 0.01289, "hc": 0.5349, "ha": 0.5663, "sc": 0.2558, "sa2": 0.317}, {"ym": "2020-07", "A": -0.00947, "rp": 0.02894, "rb": 0.03842, "ic": -0.1421, "n": 43, "herf": 0.03166, "sz": -0.00923, "hc": 0.4651, "ha": 0.3967, "sc": -0.4884, "sa2": -0.5656}, {"ym": "2020-08", "A": 0.01505, "rp": 0.01226, "rb": -0.00279, "ic": 0.1868, "n": 43, "herf": 0.03054, "sz": 0.01159, "hc": 0.5116, "ha": 0.5493, "sc": 0.0698, "sa2": 0.1868}, {"ym": "2020-09", "A": -0.01071, "rp": 0.0163, "rb": 0.027, "ic": -0.0597, "n": 43, "herf": 0.03218, "sz": 0.0015, "hc": 0.5116, "ha": 0.5438, "sc": 0.1395, "sa2": 0.1989}, {"ym": "2020-10", "A": -0.03165, "rp": 0.08776, "rb": 0.11941, "ic": -0.3202, "n": 43, "herf": 0.03208, "sz": -0.01894, "hc": 0.4419, "ha": 0.3715, "sc": -0.093, "sa2": -0.1791}, {"ym": "2020-11", "A": -0.00312, "rp": 0.07164, "rb": 0.07475, "ic": -0.179, "n": 42, "herf": 0.0322, "sz": -0.00029, "hc": 0.4048, "ha": 0.3863, "sc": -0.2143, "sa2": -0.2241}, {"ym": "2020-12", "A": 0.00164, "rp": -0.01688, "rb": -0.01852, "ic": -0.0746, "n": 40, "herf": 0.03464, "sz": -0.00596, "hc": 0.525, "ha": 0.5565, "sc": -0.05, "sa2": -0.0552}, {"ym": "2021-01", "A": -0.03805, "rp": 0.04113, "rb": 0.07917, "ic": 0.1197, "n": 39, "herf": 0.03647, "sz": -0.00311, "hc": 0.3333, "ha": 0.3203, "sc": -0.2051, "sa2": -0.1918}, {"ym": "2021-02", "A": 0.01903, "rp": 0.0305, "rb": 0.01148, "ic": -0.2005, "n": 37, "herf": 0.03857, "sz": 0.00413, "hc": 0.5135, "ha": 0.5456, "sc": 0.3243, "sa2": 0.3883}, {"ym": "2021-03", "A": 0.00154, "rp": 0.00607, "rb": 0.00453, "ic": 0.1302, "n": 37, "herf": 0.03978, "sz": 0.00173, "hc": 0.3784, "ha": 0.3661, "sc": -0.2432, "sa2": -0.2061}, {"ym": "2021-04", "A": -0.00551, "rp": 0.06555, "rb": 0.07106, "ic": -0.2001, "n": 38, "herf": 0.03597, "sz": -0.00503, "hc": 0.4211, "ha": 0.3604, "sc": -0.2368, "sa2": -0.2384}, {"ym": "2021-05", "A": 0.01495, "rp": 0.03551, "rb": 0.02056, "ic": 0.1699, "n": 38, "herf": 0.03535, "sz": 0.01004, "hc": 0.5, "ha": 0.5815, "sc": -0.3421, "sa2": -0.2824}, {"ym": "2021-06", "A": 0.0014, "rp": 0.01719, "rb": 0.01578, "ic": 0.136, "n": 37, "herf": 0.03888, "sz": 0.00127, "hc": 0.4054, "ha": 0.4724, "sc": -0.2162, "sa2": -0.2153}, {"ym": "2021-07", "A": -0.00424, "rp": 0.06172, "rb": 0.06596, "ic": 0.2265, "n": 41, "herf": 0.03556, "sz": 0.01118, "hc": 0.2927, "ha": 0.2956, "sc": 0.5366, "sa2": 0.6052}, {"ym": "2021-08", "A": -0.00354, "rp": 0.03131, "rb": 0.03485, "ic": -0.1993, "n": 41, "herf": 0.03634, "sz": -0.01252, "hc": 0.4878, "ha": 0.4168, "sc": -0.0244, "sa2": -0.086}, {"ym": "2021-09", "A": 0.00694, "rp": 0.01007, "rb": 0.00312, "ic": 0.0924, "n": 41, "herf": 0.03543, "sz": -0.0031, "hc": 0.5366, "ha": 0.5575, "sc": 0.0732, "sa2": 0.0634}, {"ym": "2021-10", "A": 0.02594, "rp": -0.00234, "rb": -0.02828, "ic": 0.1493, "n": 41, "herf": 0.03359, "sz": 0.00658, "hc": 0.5366, "ha": 0.5795, "sc": 0.1463, "sa2": 0.268}, {"ym": "2021-11", "A": 0.00745, "rp": 0.03164, "rb": 0.0242, "ic": 0.1819, "n": 41, "herf": 0.03487, "sz": 0.00977, "hc": 0.4634, "ha": 0.5409, "sc": -0.1951, "sa2": -0.1546}, {"ym": "2021-12", "A": -0.01164, "rp": -0.0164, "rb": -0.00475, "ic": -0.1316, "n": 41, "herf": 0.03665, "sz": -0.01176, "hc": 0.5366, "ha": 0.4948, "sc": -0.0976, "sa2": -0.2386}, {"ym": "2022-01", "A": -0.0, "rp": -0.03946, "rb": -0.03946, "ic": 0.0334, "n": 40, "herf": 0.03612, "sz": 0.00248, "hc": 0.475, "ha": 0.518, "sc": 0.45, "sa2": 0.4991}, {"ym": "2022-02", "A": -0.00828, "rp": 0.03315, "rb": 0.04143, "ic": -0.162, "n": 38, "herf": 0.03809, "sz": 0.00147, "hc": 0.3684, "ha": 0.4161, "sc": 0.0789, "sa2": 0.1288}, {"ym": "2022-03", "A": -0.00901, "rp": -0.01614, "rb": -0.00713, "ic": -0.2793, "n": 38, "herf": 0.03939, "sz": -0.02662, "hc": 0.6316, "ha": 0.5139, "sc": -0.1842, "sa2": -0.3448}, {"ym": "2022-04", "A": -0.01247, "rp": -0.05472, "rb": -0.04225, "ic": 0.0288, "n": 38, "herf": 0.03711, "sz": 0.00419, "hc": 0.4737, "ha": 0.4808, "sc": 0.1842, "sa2": 0.1839}, {"ym": "2022-05", "A": 0.01066, "rp": -0.03981, "rb": -0.05047, "ic": 0.1298, "n": 39, "herf": 0.03669, "sz": 0.00575, "hc": 0.5385, "ha": 0.5941, "sc": 0.0, "sa2": 0.0403}, {"ym": "2022-06", "A": -0.00015, "rp": 0.09715, "rb": 0.0973, "ic": -0.2854, "n": 39, "herf": 0.03717, "sz": -0.01408, "hc": 0.5385, "ha": 0.4646, "sc": 0.1538, "sa2": 0.0356}, {"ym": "2022-07", "A": 0.00533, "rp": 0.05216, "rb": 0.04683, "ic": -0.0637, "n": 39, "herf": 0.03633, "sz": -0.01228, "hc": 0.5897, "ha": 0.5532, "sc": -0.0256, "sa2": -0.1443}, {"ym": "2022-08", "A": 0.00669, "rp": -0.02536, "rb": -0.03205, "ic": 0.1741, "n": 39, "herf": 0.03506, "sz": 0.00469, "hc": 0.5128, "ha": 0.5258, "sc": -0.1026, "sa2": -0.0648}, {"ym": "2022-09", "A": 0.00259, "rp": 0.04351, "rb": 0.04092, "ic": 0.0569, "n": 38, "herf": 0.03498, "sz": -0.00103, "hc": 0.5676, "ha": 0.6114, "sc": 0.2703, "sa2": 0.2927}, {"ym": "2022-10", "A": -0.0173, "rp": 0.01693, "rb": 0.03423, "ic": -0.3015, "n": 38, "herf": 0.03512, "sz": -0.00401, "hc": 0.3784, "ha": 0.3651, "sc": -0.027, "sa2": -0.0667}, {"ym": "2022-11", "A": -0.00078, "rp": -0.03196, "rb": -0.03118, "ic": 0.0301, "n": 38, "herf": 0.03575, "sz": -0.00245, "hc": 0.4865, "ha": 0.4394, "sc": -0.0811, "sa2": -0.0913}, {"ym": "2022-12", "A": 0.02563, "rp": -0.00742, "rb": -0.03305, "ic": 0.2053, "n": 38, "herf": 0.03401, "sz": 0.00867, "hc": 0.5946, "ha": 0.6236, "sc": 0.0811, "sa2": 0.139}, {"ym": "2023-01", "A": 0.00838, "rp": -0.01875, "rb": -0.02713, "ic": 0.2448, "n": 38, "herf": 0.03458, "sz": 0.00518, "hc": 0.5405, "ha": 0.5891, "sc": 0.1622, "sa2": 0.2002}, {"ym": "2023-02", "A": -0.00208, "rp": 0.00072, "rb": 0.0028, "ic": 0.0985, "n": 38, "herf": 0.03504, "sz": -0.00094, "hc": 0.5676, "ha": 0.5654, "sc": 0.0811, "sa2": 0.0716}, {"ym": "2023-03", "A": -0.01431, "rp": 0.03144, "rb": 0.04575, "ic": -0.1707, "n": 38, "herf": 0.03532, "sz": -0.00859, "hc": 0.5946, "ha": 0.5291, "sc": -0.2973, "sa2": -0.3666}, {"ym": "2023-04", "A": 0.00348, "rp": 0.04129, "rb": 0.03782, "ic": 0.063, "n": 38, "herf": 0.03479, "sz": 0.00608, "hc": 0.5526, "ha": 0.5589, "sc": -0.0263, "sa2": -0.0133}, {"ym": "2023-05", "A": 0.00805, "rp": 0.05157, "rb": 0.04351, "ic": 0.0552, "n": 36, "herf": 0.03601, "sz": -0.00051, "hc": 0.5, "ha": 0.4767, "sc": -0.1111, "sa2": -0.1158}, {"ym": "2023-06", "A": 0.009, "rp": 0.04831, "rb": 0.03932, "ic": -0.3659, "n": 32, "herf": 0.03861, "sz": -0.01045, "hc": 0.5312, "ha": 0.4567, "sc": 0.0, "sa2": -0.0473}, {"ym": "2023-07", "A": 0.00454, "rp": -0.0015, "rb": -0.00604, "ic": 0.1107, "n": 33, "herf": 0.03769, "sz": 0.0001, "hc": 0.4375, "ha": 0.4558, "sc": -0.4062, "sa2": -0.4183}, {"ym": "2023-08", "A": 0.01059, "rp": 0.03252, "rb": 0.02193, "ic": 0.0127, "n": 33, "herf": 0.0365, "sz": -0.0009, "hc": 0.5455, "ha": 0.5431, "sc": 0.1212, "sa2": 0.125}, {"ym": "2023-09", "A": -0.0041, "rp": -0.03184, "rb": -0.02774, "ic": -0.0734, "n": 33, "herf": 0.0368, "sz": -0.00432, "hc": 0.3636, "ha": 0.3127, "sc": -0.0606, "sa2": -0.0797}, {"ym": "2023-10", "A": 0.01247, "rp": 0.08398, "rb": 0.07151, "ic": -0.1461, "n": 32, "herf": 0.03686, "sz": -0.00879, "hc": 0.5, "ha": 0.4508, "sc": 0.0312, "sa2": 0.0042}, {"ym": "2023-11", "A": 0.0122, "rp": 0.09233, "rb": 0.08013, "ic": 0.0618, "n": 33, "herf": 0.03552, "sz": -0.0031, "hc": 0.5152, "ha": 0.5066, "sc": 0.2727, "sa2": 0.2784}, {"ym": "2023-12", "A": 0.04798, "rp": 0.06749, "rb": 0.01951, "ic": -0.0582, "n": 34, "herf": 0.03509, "sz": -0.00312, "hc": 0.5588, "ha": 0.5614, "sc": 0.0882, "sa2": 0.0808}, {"ym": "2024-01", "A": 0.00268, "rp": 0.01842, "rb": 0.01574, "ic": 0.0705, "n": 38, "herf": 0.03264, "sz": -0.00032, "hc": 0.4474, "ha": 0.4416, "sc": 0.2632, "sa2": 0.2363}, {"ym": "2024-02", "A": -0.00277, "rp": 0.00561, "rb": 0.00838, "ic": -0.0764, "n": 41, "herf": 0.03093, "sz": -0.00599, "hc": 0.4634, "ha": 0.4246, "sc": 0.5122, "sa2": 0.4934}, {"ym": "2024-03", "A": 0.02683, "rp": 0.06348, "rb": 0.03665, "ic": -0.1511, "n": 44, "herf": 0.02738, "sz": -0.00911, "hc": 0.5909, "ha": 0.5841, "sc": -0.2955, "sa2": -0.3496}, {"ym": "2024-04", "A": 0.0283, "rp": 0.03561, "rb": 0.00731, "ic": 0.1705, "n": 50, "herf": 0.02447, "sz": 0.00491, "hc": 0.5, "ha": 0.4859, "sc": 0.28, "sa2": 0.29}, {"ym": "2024-05", "A": 0.02009, "rp": 0.09061, "rb": 0.07051, "ic": -0.2374, "n": 57, "herf": 0.02061, "sz": -0.00569, "hc": 0.5088, "ha": 0.4479, "sc": -0.0702, "sa2": -0.0988}, {"ym": "2024-06", "A": 0.02088, "rp": 0.06479, "rb": 0.04391, "ic": -0.1004, "n": 59, "herf": 0.02008, "sz": -0.00598, "hc": 0.5263, "ha": 0.5125, "sc": 0.0351, "sa2": -0.0122}, {"ym": "2024-07", "A": 0.02112, "rp": 0.03147, "rb": 0.01036, "ic": 0.0291, "n": 72, "herf": 0.01619, "sz": -0.00438, "hc": 0.4789, "ha": 0.4958, "sc": 0.0845, "sa2": 0.1041}, {"ym": "2024-08", "A": -0.00354, "rp": 0.01813, "rb": 0.02167, "ic": 0.2068, "n": 69, "herf": 0.01635, "sz": 0.0046, "hc": 0.4412, "ha": 0.4741, "sc": 0.1618, "sa2": 0.1859}, {"ym": "2024-09", "A": 0.00086, "rp": -0.06267, "rb": -0.06352, "ic": -0.2214, "n": 68, "herf": 0.01716, "sz": -0.00579, "hc": 0.5735, "ha": 0.5137, "sc": -0.0441, "sa2": -0.0364}, {"ym": "2024-10", "A": 0.00215, "rp": 0.0026, "rb": 0.00046, "ic": 0.1475, "n": 64, "herf": 0.01863, "sz": 0.0046, "hc": 0.4844, "ha": 0.5185, "sc": -0.0625, "sa2": -0.0194}, {"ym": "2024-11", "A": 0.00312, "rp": -0.01054, "rb": -0.01366, "ic": 0.0056, "n": 65, "herf": 0.01867, "sz": 0.00045, "hc": 0.4308, "ha": 0.4496, "sc": 0.0, "sa2": -0.0257}, {"ym": "2024-12", "A": -0.02429, "rp": -0.05899, "rb": -0.0347, "ic": 0.1571, "n": 67, "herf": 0.01779, "sz": 0.00479, "hc": 0.3582, "ha": 0.3775, "sc": 0.1791, "sa2": 0.2138}, {"ym": "2025-01", "A": -0.01239, "rp": -0.09025, "rb": -0.07786, "ic": 0.2533, "n": 68, "herf": 0.01824, "sz": 0.01114, "hc": 0.3824, "ha": 0.4372, "sc": 0.2794, "sa2": 0.3657}, {"ym": "2025-02", "A": 0.00979, "rp": 0.08331, "rb": 0.07353, "ic": 0.1204, "n": 65, "herf": 0.01979, "sz": 0.00075, "hc": 0.5231, "ha": 0.5192, "sc": 0.2462, "sa2": 0.2631}, {"ym": "2025-03", "A": -0.01156, "rp": 0.02095, "rb": 0.03251, "ic": 0.053, "n": 63, "herf": 0.02012, "sz": -0.00181, "hc": 0.4444, "ha": 0.4533, "sc": -0.0952, "sa2": -0.0826}, {"ym": "2025-04", "A": 0.03356, "rp": 0.07009, "rb": 0.03652, "ic": -0.3, "n": 62, "herf": 0.02088, "sz": -0.00872, "hc": 0.5, "ha": 0.4203, "sc": -0.1774, "sa2": -0.2939}, {"ym": "2025-05", "A": -0.0078, "rp": 0.02987, "rb": 0.03767, "ic": 0.0767, "n": 63, "herf": 0.02021, "sz": -0.00147, "hc": 0.4444, "ha": 0.4655, "sc": 0.0159, "sa2": 0.025}, {"ym": "2025-06", "A": -0.00272, "rp": -0.03099, "rb": -0.02827, "ic": -0.1781, "n": 64, "herf": 0.02022, "sz": -0.00673, "hc": 0.5312, "ha": 0.4797, "sc": -0.1406, "sa2": -0.2134}, {"ym": "2025-07", "A": -0.00465, "rp": -0.02282, "rb": -0.01817, "ic": 0.028, "n": 65, "herf": 0.01953, "sz": -0.0029, "hc": 0.4769, "ha": 0.4556, "sc": 0.1385, "sa2": 0.1446}, {"ym": "2025-08", "A": 0.00563, "rp": 0.01795, "rb": 0.01232, "ic": -0.0925, "n": 65, "herf": 0.01953, "sz": -0.00258, "hc": 0.5538, "ha": 0.4917, "sc": 0.1231, "sa2": 0.1169}, {"ym": "2025-09", "A": 0.00571, "rp": 0.04936, "rb": 0.04366, "ic": 0.1928, "n": 63, "herf": 0.02024, "sz": 0.00461, "hc": 0.4127, "ha": 0.4251, "sc": 0.1111, "sa2": 0.1461}, {"ym": "2025-10", "A": -0.01484, "rp": -0.00488, "rb": 0.00996, "ic": 0.2402, "n": 64, "herf": 0.02072, "sz": 0.00766, "hc": 0.3906, "ha": 0.4742, "sc": 0.25, "sa2": 0.3704}, {"ym": "2025-11", "A": -0.01333, "rp": -0.0159, "rb": -0.00257, "ic": -0.1642, "n": 64, "herf": 0.02108, "sz": -0.0036, "hc": 0.375, "ha": 0.3392, "sc": 0.2344, "sa2": 0.1783}, {"ym": "2025-12", "A": -0.00805, "rp": -0.04079, "rb": -0.03273, "ic": 0.0644, "n": 63, "herf": 0.02188, "sz": -0.00027, "hc": 0.4603, "ha": 0.4727, "sc": 0.1905, "sa2": 0.2193}, {"ym": "2026-01", "A": 0.01779, "rp": 0.0223, "rb": 0.00452, "ic": 0.0515, "n": 66, "herf": 0.02151, "sz": -0.00443, "hc": 0.5, "ha": 0.5057, "sc": 0.1364, "sa2": 0.1152}, {"ym": "2026-02", "A": -0.01033, "rp": -0.12397, "rb": -0.11365, "ic": -0.0445, "n": 66, "herf": 0.02151, "sz": -0.00357, "hc": 0.4545, "ha": 0.4161, "sc": 0.1061, "sa2": 0.0888}, {"ym": "2026-03", "A": 0.02828, "rp": 0.13352, "rb": 0.10525, "ic": -0.3134, "n": 66, "herf": 0.0208, "sz": -0.01893, "hc": 0.5758, "ha": 0.4454, "sc": -0.3333, "sa2": -0.4786}, {"ym": "2026-04", "A": 0.03647, "rp": 0.03633, "rb": -0.00013, "ic": 0.1663, "n": 61, "herf": 0.02096, "sz": 0.00807, "hc": 0.4426, "ha": 0.4571, "sc": 0.0328, "sa2": 0.054}, {"ym": "2026-05", "A": 0.01112, "rp": 0.0338, "rb": 0.02269, "ic": 0.1205, "n": 59, "herf": 0.02159, "sz": 0.00578, "hc": 0.5593, "ha": 0.598, "sc": -0.0508, "sa2": -0.0036}], "portfolio": {"asof": "2026-05-31", "n_equity": 59, "equity_pct_fund": 96.6, "asset_alloc": {"Equity": 96.6}, "sector_cover": 92.1, "sector_now": [{"sector": "Financial Services", "pct": 21.2}, {"sector": "Capital Goods", "pct": 18.5}, {"sector": "Automobile and Auto Components", "pct": 9.2}, {"sector": "Fast Moving Consumer Goods", "pct": 8.4}, {"sector": "Unclassified", "pct": 7.9}, {"sector": "Healthcare", "pct": 7.8}, {"sector": "Information Technology", "pct": 4.5}, {"sector": "Chemicals", "pct": 3.5}, {"sector": "Telecommunication", "pct": 3.2}, {"sector": "Consumer Services", "pct": 3.1}, {"sector": "Power", "pct": 2.7}, {"sector": "Services", "pct": 2.0}, {"sector": "Construction Materials", "pct": 1.9}, {"sector": "Consumer Durables", "pct": 1.8}, {"sector": "Oil Gas & Consumable Fuels", "pct": 1.6}, {"sector": "Construction", "pct": 1.5}, {"sector": "Media Entertainment & Publication", "pct": 1.2}], "top_holdings": [{"name": "HDFC Bank Ltd", "symbol": "HDFCBANK", "pct": 5.32, "sector": "Financial Services", "vst_id": "VST02887"}, {"name": "Garware Hi Tech Films Ltd", "symbol": "GRWRHITECH", "pct": 4.04, "sector": "Capital Goods", "vst_id": "VST00757"}, {"name": "ICICI Bank Ltd", "symbol": "ICICIBANK", "pct": 3.67, "sector": "Financial Services", "vst_id": "VST02975"}, {"name": "Avalon Technologies Ltd", "symbol": "AVALON", "pct": 3.34, "sector": "Capital Goods", "vst_id": "VST00391"}, {"name": "Axis Bank Ltd", "symbol": "AXISBANK", "pct": 2.88, "sector": "Financial Services", "vst_id": "VST02217"}, {"name": "Tata Consultancy Services Ltd", "symbol": "TCS", "pct": 2.72, "sector": "Information Technology", "vst_id": "VST04256"}, {"name": "NTPC Ltd", "symbol": "NTPC", "pct": 2.63, "sector": "Power", "vst_id": "VST03610"}, {"name": "Bharat Electronics Ltd", "symbol": "BEL", "pct": 2.48, "sector": "Capital Goods", "vst_id": "VST02277"}, {"name": "Allied Blenders & Distillers Ltd", "symbol": "ABDL", "pct": 2.25, "sector": "Fast Moving Consumer Goods", "vst_id": "VST01115"}, {"name": "Kotak Mahindra Bank Ltd", "symbol": "KOTAKBANK", "pct": 2.2, "sector": "Financial Services", "vst_id": "VST03264"}, {"name": "Apollo Hospitals Enterprise Ltd", "symbol": "APOLLOHOSP", "pct": 2.15, "sector": "Healthcare", "vst_id": "VST02130"}, {"name": "Interglobe Aviation Ltd", "symbol": "INDIGO", "pct": 1.96, "sector": "Services", "vst_id": "VST01230"}, {"name": "Neuland Laboratories Ltd", "symbol": "NEULANDLAB", "pct": 1.93, "sector": "Healthcare", "vst_id": "VST03568"}, {"name": "Tata Communications Ltd", "symbol": "TATACOMM", "pct": 1.9, "sector": "Telecommunication", "vst_id": "VST04227"}, {"name": "Pidilite Industries Ltd", "symbol": "PIDILITIND", "pct": 1.89, "sector": "Chemicals", "vst_id": "VST03732"}], "by_sector": [{"sector": "Financial Services", "pct": 20.44, "names": [{"name": "HDFC Bank Ltd", "symbol": "HDFCBANK", "pct": 5.32}, {"name": "ICICI Bank Ltd", "symbol": "ICICIBANK", "pct": 3.67}, {"name": "Axis Bank Ltd", "symbol": "AXISBANK", "pct": 2.88}, {"name": "Kotak Mahindra Bank Ltd", "symbol": "KOTAKBANK", "pct": 2.2}, {"name": "Shriram Finance Ltd", "symbol": "SHRIRAMFIN", "pct": 1.84}, {"name": "Cholamandalam Financial Holdings Ltd", "symbol": "CHOLAHLDNG", "pct": 1.37}, {"name": "Multi Commodity Exchange of India Ltd", "symbol": "MCX", "pct": 1.19}, {"name": "Sundaram Finance Ltd", "symbol": "SUNDARMFIN", "pct": 1.02}, {"name": "Ujjivan Small Finance Bank Ltd", "symbol": "UJJIVANSFB", "pct": 0.95}]}, {"sector": "Capital Goods", "pct": 17.92, "names": [{"name": "Garware Hi Tech Films Ltd", "symbol": "GRWRHITECH", "pct": 4.04}, {"name": "Avalon Technologies Ltd", "symbol": "AVALON", "pct": 3.34}, {"name": "Bharat Electronics Ltd", "symbol": "BEL", "pct": 2.48}, {"name": "Azad Engineering Ltd", "symbol": "AZAD", "pct": 1.29}, {"name": "Tata Motors Ltd", "symbol": "TMCV", "pct": 1.2}, {"name": "Hindustan Aeronautics Ltd", "symbol": "HAL", "pct": 1.14}, {"name": "Surya Roshni Ltd", "symbol": "SURYAROSNI", "pct": 1.14}, {"name": "Shakti Pumps (India) Ltd", "symbol": "SHAKTIPUMP", "pct": 1.01}, {"name": "RHI Magnesita India Ltd", "symbol": "RHIM", "pct": 0.9}, {"name": "Ratnamani Metals & Tubes Ltd", "symbol": "RATNAMANI", "pct": 0.76}, {"name": "Maharashtra Seamless Ltd", "symbol": "MAHSEAMLES", "pct": 0.62}]}, {"sector": "Automobile and Auto Components", "pct": 8.88, "names": [{"name": "Tata Motors Passenger Vehicles Ltd", "symbol": "TMPV", "pct": 1.76}, {"name": "Bajaj Auto Ltd", "symbol": "BAJAJ-AUTO", "pct": 1.7}, {"name": "Samvardhana Motherson International Ltd", "symbol": "MOTHERSON", "pct": 1.52}, {"name": "Pricol Ltd", "symbol": "PRICOLLTD", "pct": 1.44}, {"name": "Mahindra & Mahindra Ltd", "symbol": "M&M", "pct": 1.25}, {"name": "Maruti Suzuki India Ltd", "symbol": "MARUTI", "pct": 1.21}]}, {"sector": "Fast Moving Consumer Goods", "pct": 8.15, "names": [{"name": "Allied Blenders & Distillers Ltd", "symbol": "ABDL", "pct": 2.25}, {"name": "Radico Khaitan Ltd", "symbol": "RADICO", "pct": 1.72}, {"name": "Hindustan Unilever Ltd", "symbol": "HINDUNILVR", "pct": 1.59}, {"name": "Godfrey Phillips India Ltd", "symbol": "GODFRYPHLP", "pct": 1.4}, {"name": "Bikaji Foods International Ltd", "symbol": "BIKAJI", "pct": 1.19}]}, {"sector": "Unclassified", "pct": 7.59, "names": [{"name": "DEE Development Engineers Ltd", "symbol": "DEEDEV", "pct": 1.73}, {"name": "Gujarat Gas Ltd", "symbol": "GUJGASLTD", "pct": 1.4}, {"name": "MAS Financial Services Ltd", "symbol": "MASFIN", "pct": 1.28}, {"name": "ISGEC Heavy Engineering  Ltd", "symbol": "ISGEC", "pct": 1.04}, {"name": "Vinati Organics Ltd", "symbol": "VINATIORGA", "pct": 0.78}, {"name": "Bharat Bijlee Ltd", "symbol": "BBL", "pct": 0.74}, {"name": "Divgi Torqtransfer Systems Ltd", "symbol": "DIVGIITTS", "pct": 0.62}]}, {"sector": "Healthcare", "pct": 7.58, "names": [{"name": "Apollo Hospitals Enterprise Ltd", "symbol": "APOLLOHOSP", "pct": 2.15}, {"name": "Neuland Laboratories Ltd", "symbol": "NEULANDLAB", "pct": 1.93}, {"name": "Anthem Biosciences Ltd", "symbol": "ANTHEM", "pct": 1.27}, {"name": "Abbott India Ltd", "symbol": "ABBOTINDIA", "pct": 1.23}, {"name": "Sun Pharmaceutical Industries Ltd", "symbol": "SUNPHARMA", "pct": 1.0}]}, {"sector": "Information Technology", "pct": 4.34, "names": [{"name": "Tata Consultancy Services Ltd", "symbol": "TCS", "pct": 2.72}, {"name": "Mphasis Ltd", "symbol": "MPHASIS", "pct": 0.87}, {"name": "L&T Technology Services Ltd", "symbol": "LTTS", "pct": 0.75}]}, {"sector": "Chemicals", "pct": 3.34, "names": [{"name": "Pidilite Industries Ltd", "symbol": "PIDILITIND", "pct": 1.89}, {"name": "SRF Ltd", "symbol": "SRF", "pct": 1.45}]}, {"sector": "Telecommunication", "pct": 3.08, "names": [{"name": "Tata Communications Ltd", "symbol": "TATACOMM", "pct": 1.9}, {"name": "Bharti Airtel Ltd", "symbol": "BHARTIARTL", "pct": 1.18}]}, {"sector": "Consumer Services", "pct": 2.99, "names": [{"name": "Arvind Fashions Ltd", "symbol": "ARVINDFASN", "pct": 1.67}, {"name": "EIH Ltd", "symbol": "EIHOTEL", "pct": 1.32}]}, {"sector": "Power", "pct": 2.63, "names": [{"name": "NTPC Ltd", "symbol": "NTPC", "pct": 2.63}]}, {"sector": "Services", "pct": 1.96, "names": [{"name": "Interglobe Aviation Ltd", "symbol": "INDIGO", "pct": 1.96}]}, {"sector": "Construction Materials", "pct": 1.85, "names": [{"name": "Grasim Industries Ltd", "symbol": "GRASIM", "pct": 1.85}]}, {"sector": "Consumer Durables", "pct": 1.71, "names": [{"name": "LG Electronics India Ltd", "symbol": "LGEINDIA", "pct": 1.71}]}, {"sector": "Oil Gas & Consumable Fuels", "pct": 1.57, "names": [{"name": "Oil India Ltd", "symbol": "OIL", "pct": 1.57}]}, {"sector": "Construction", "pct": 1.48, "names": [{"name": "Techno Electric & Engineering Company Ltd", "symbol": "TECHNOE", "pct": 1.48}]}, {"sector": "Media Entertainment & Publication", "pct": 1.12, "names": [{"name": "Saregama India Ltd", "symbol": "SAREGAMA", "pct": 1.12}]}], "rotation": {"dates": ["2019-03", "2019-09", "2020-03", "2020-09", "2021-03", "2021-09", "2022-03", "2022-09", "2023-03", "2023-09", "2024-03", "2024-09", "2025-03", "2025-09", "2026-03", "2026-05"], "sectors": ["Financial Services", "Information Technology", "Capital Goods", "Healthcare", "Automobile and Auto Components", "Power", "Oil Gas & Consumable Fuels", "Fast Moving Consumer Goods", "Consumer Durables", "Unclassified", "Other"], "matrix": [[6.0, 15.2, 14.2, 10.4, 10.6, 10.3, 9.8, 10.9, 10.3, 14.8, 22.7, 20.2, 25.4, 23.3, 22.9, 21.2], [23.4, 13.9, 13.5, 20.0, 20.4, 19.0, 20.6, 15.1, 15.7, 14.8, 13.2, 7.6, 6.6, 6.6, 5.2, 4.5], [6.7, 9.0, 11.7, 13.2, 11.7, 12.4, 13.2, 13.2, 13.4, 10.8, 10.2, 9.3, 13.4, 14.3, 16.6, 18.5], [24.3, 11.2, 18.1, 15.4, 10.1, 6.5, 5.8, 4.5, 3.2, 3.0, 2.9, 3.5, 4.1, 5.9, 7.9, 7.8], [6.6, 3.7, 3.0, 4.2, 8.3, 7.7, 8.6, 12.4, 12.1, 11.9, 12.2, 8.5, 8.8, 7.7, 7.4, 9.2], [0.0, 8.1, 8.9, 7.2, 7.7, 10.8, 12.2, 12.3, 12.8, 16.1, 10.5, 5.4, 4.5, 2.1, 3.0, 2.7], [7.5, 17.0, 11.0, 10.3, 12.1, 11.8, 7.5, 7.2, 8.4, 5.8, 4.6, 3.4, 1.0, 0.8, 1.7, 1.6], [4.3, 4.0, 3.1, 2.7, 3.2, 2.9, 3.0, 3.8, 3.4, 3.0, 4.1, 9.8, 9.2, 10.4, 7.4, 8.4], [5.7, 4.1, 5.2, 4.9, 6.5, 6.7, 7.3, 7.7, 7.4, 6.0, 4.8, 0.8, 0.0, 1.2, 1.7, 1.8], [0.0, 2.1, 2.3, 2.0, 1.5, 1.4, 1.3, 1.7, 2.0, 4.5, 7.1, 12.7, 9.7, 9.7, 8.1, 7.9], [15.6, 11.6, 9.0, 9.5, 7.9, 10.5, 10.7, 11.1, 11.3, 9.3, 7.8, 18.7, 17.3, 18.0, 18.2, 16.4]]}, "conc_ts": [{"ym": "2019-03", "top10": 68.1, "n": 20}, {"ym": "2019-09", "top10": 32.7, "n": 51}, {"ym": "2020-03", "top10": 37.4, "n": 47}, {"ym": "2020-09", "top10": 40.7, "n": 43}, {"ym": "2021-03", "top10": 45.6, "n": 37}, {"ym": "2021-09", "top10": 44.0, "n": 41}, {"ym": "2022-03", "top10": 47.1, "n": 38}, {"ym": "2022-09", "top10": 46.3, "n": 38}, {"ym": "2023-03", "top10": 46.6, "n": 38}, {"ym": "2023-09", "top10": 47.0, "n": 33}, {"ym": "2024-03", "top10": 37.1, "n": 44}, {"ym": "2024-09", "top10": 25.0, "n": 68}, {"ym": "2025-03", "top10": 30.2, "n": 63}, {"ym": "2025-09", "top10": 29.5, "n": 63}, {"ym": "2026-03", "top10": 32.2, "n": 66}, {"ym": "2026-05", "top10": 32.6, "n": 59}]}}