{"navindia_code": "40637", "scheme_name": "Kotak Focused Fund (G)", "amc": "Kotak Mahindra Mutual Fund", "sebi_category": "Focused Fund", "benchmark": "NIFTY 500", "n_months": 83, "years": 6.9, "gappy": false, "is_thematic": false, "is_hybrid": false, "excess_cagr": 0.0174, "cagr_paper": 0.1744, "cagr_bench": 0.157, "info_ratio": 0.3957, "t_stat": 1.0408, "years_needed": 24.5287, "tracking_error": 0.0375, "ic_mean": -0.0106, "ic_t": -0.4426, "sizing_edge_cum": -0.2743, "hit_rate_monthly": 0.5422, "mag_hit": 0.5695, "slugging": 1.12, "avg_win": 0.00934, "avg_loss": -0.00836, "port_hit_cnt": 0.4904, "port_hit_aum": 0.4904, "port_slug_cnt": 0.0304, "port_slug_aum": 0.0256, "herfindahl": 0.038, "herfindahl_avg": 0.0431, "eff_n": 26.3, "avg_names": 29.7, "boot_meanA_lo": -0.00083, "boot_meanA_hi": 0.00326, "boot_p_positive": 0.8835, "verdict": "ahead but not yet significant", "verdict_why": "+1.7%/yr, t=1.0 (need t≥2 & bootstrap≥95%; ~25y more)", "basis": "GROSS holdings-implied total-return excess vs the SEBI-category benchmark (pre-cost, pre-cash-drag, pre-factor-deflation); domestic equity sleeve only, month-end snapshots. ‘Holding-rank IC’ is a cap-tilt-contaminated proxy, not pure active-weight selection (needs point-in-time benchmark weights).", "ts": [{"ym": "2019-07", "A": 0.0278, "rp": 0.02242, "rb": -0.00538, "ic": -0.3502, "n": 19, "herf": 0.08263, "sz": -0.01638, "hc": 0.6842, "ha": 0.5752, "sc": 0.3684, "sa2": 0.27}, {"ym": "2019-08", "A": -0.00094, "rp": 0.0398, "rb": 0.04074, "ic": -0.186, "n": 30, "herf": 0.04789, "sz": 0.00038, "hc": 0.5, "ha": 0.5627, "sc": -0.1333, "sa2": -0.1364}, {"ym": "2019-09", "A": -0.00898, "rp": 0.02974, "rb": 0.03872, "ic": -0.0966, "n": 30, "herf": 0.04591, "sz": -0.00319, "hc": 0.6333, "ha": 0.5838, "sc": 0.1667, "sa2": 0.1581}, {"ym": "2019-10", "A": -0.002, "rp": 0.01112, "rb": 0.01311, "ic": -0.2127, "n": 30, "herf": 0.04528, "sz": 0.00079, "hc": 0.5333, "ha": 0.5757, "sc": 0.1333, "sa2": 0.1597}, {"ym": "2019-11", "A": 0.00273, "rp": 0.00881, "rb": 0.00608, "ic": -0.0841, "n": 30, "herf": 0.04525, "sz": -0.00052, "hc": 0.5333, "ha": 0.5022, "sc": 0.1, "sa2": 0.1331}, {"ym": "2019-12", "A": 0.01829, "rp": 0.01729, "rb": -0.00099, "ic": -0.1544, "n": 30, "herf": 0.04521, "sz": -0.01637, "hc": 0.5667, "ha": 0.4487, "sc": -0.2, "sa2": -0.3133}, {"ym": "2020-01", "A": 0.01336, "rp": -0.04941, "rb": -0.06277, "ic": 0.3146, "n": 30, "herf": 0.04289, "sz": 0.00174, "hc": 0.6667, "ha": 0.7398, "sc": 0.2333, "sa2": 0.201}, {"ym": "2020-02", "A": -0.01399, "rp": -0.25434, "rb": -0.24035, "ic": 0.0527, "n": 29, "herf": 0.0433, "sz": 0.00291, "hc": 0.4828, "ha": 0.4648, "sc": 0.2414, "sa2": 0.2608}, {"ym": "2020-03", "A": -0.00053, "rp": 0.14481, "rb": 0.14535, "ic": 0.1366, "n": 30, "herf": 0.0436, "sz": 0.00423, "hc": 0.4667, "ha": 0.5052, "sc": -0.1, "sa2": -0.0491}, {"ym": "2020-04", "A": -0.01359, "rp": -0.03669, "rb": -0.0231, "ic": 0.3326, "n": 30, "herf": 0.04384, "sz": 0.01245, "hc": 0.4, "ha": 0.4755, "sc": 0.0, "sa2": 0.0396}, {"ym": "2020-05", "A": 0.00311, "rp": 0.08704, "rb": 0.08394, "ic": -0.1562, "n": 29, "herf": 0.04381, "sz": -0.00998, "hc": 0.4138, "ha": 0.392, "sc": -0.4483, "sa2": -0.4485}, {"ym": "2020-06", "A": 0.00077, "rp": 0.06893, "rb": 0.06816, "ic": -0.17, "n": 30, "herf": 0.04311, "sz": 0.00154, "hc": 0.3667, "ha": 0.3882, "sc": 0.2667, "sa2": 0.3036}, {"ym": "2020-07", "A": -0.02668, "rp": 0.01174, "rb": 0.03842, "ic": -0.1284, "n": 30, "herf": 0.04582, "sz": -0.00181, "hc": 0.3333, "ha": 0.3062, "sc": -0.6333, "sa2": -0.6651}, {"ym": "2020-08", "A": 0.01899, "rp": 0.0162, "rb": -0.00279, "ic": -0.278, "n": 30, "herf": 0.04553, "sz": -0.01051, "hc": 0.6667, "ha": 0.6241, "sc": 0.1667, "sa2": 0.1799}, {"ym": "2020-09", "A": -0.00758, "rp": 0.01942, "rb": 0.027, "ic": 0.0633, "n": 29, "herf": 0.04639, "sz": 0.00211, "hc": 0.5172, "ha": 0.5648, "sc": 0.2414, "sa2": 0.2607}, {"ym": "2020-10", "A": -0.01483, "rp": 0.10459, "rb": 0.11941, "ic": -0.1484, "n": 30, "herf": 0.04647, "sz": -0.00587, "hc": 0.5333, "ha": 0.5084, "sc": -0.0333, "sa2": 0.0028}, {"ym": "2020-11", "A": -0.01476, "rp": 0.05999, "rb": 0.07475, "ic": 0.1769, "n": 30, "herf": 0.04692, "sz": 0.0052, "hc": 0.4, "ha": 0.4366, "sc": -0.3, "sa2": -0.2942}, {"ym": "2020-12", "A": 0.02369, "rp": 0.00517, "rb": -0.01852, "ic": -0.0778, "n": 29, "herf": 0.04771, "sz": -0.00836, "hc": 0.6552, "ha": 0.6187, "sc": 0.1379, "sa2": 0.0805}, {"ym": "2021-01", "A": 0.01185, "rp": 0.09103, "rb": 0.07917, "ic": -0.0469, "n": 30, "herf": 0.04551, "sz": -0.00287, "hc": 0.5667, "ha": 0.5893, "sc": 0.0, "sa2": -0.0276}, {"ym": "2021-02", "A": 0.00168, "rp": 0.01315, "rb": 0.01148, "ic": -0.3264, "n": 30, "herf": 0.0451, "sz": -0.01085, "hc": 0.4667, "ha": 0.3816, "sc": 0.3333, "sa2": 0.2785}, {"ym": "2021-03", "A": -0.01873, "rp": -0.0142, "rb": 0.00453, "ic": -0.0745, "n": 30, "herf": 0.04427, "sz": -0.00066, "hc": 0.2667, "ha": 0.2415, "sc": -0.3333, "sa2": -0.3181}, {"ym": "2021-04", "A": -0.00679, "rp": 0.06427, "rb": 0.07106, "ic": 0.0416, "n": 30, "herf": 0.04475, "sz": 0.00321, "hc": 0.4, "ha": 0.4862, "sc": -0.3, "sa2": -0.2553}, {"ym": "2021-05", "A": 0.0178, "rp": 0.03836, "rb": 0.02056, "ic": -0.4652, "n": 30, "herf": 0.04522, "sz": -0.01573, "hc": 0.6333, "ha": 0.5013, "sc": -0.2, "sa2": -0.393}, {"ym": "2021-06", "A": 0.00752, "rp": 0.02331, "rb": 0.01578, "ic": 0.1119, "n": 30, "herf": 0.04476, "sz": 0.00041, "hc": 0.5333, "ha": 0.5834, "sc": -0.2667, "sa2": -0.2889}, {"ym": "2021-07", "A": -0.00499, "rp": 0.06097, "rb": 0.06596, "ic": 0.2174, "n": 30, "herf": 0.04616, "sz": 0.00524, "hc": 0.4333, "ha": 0.4116, "sc": 0.6333, "sa2": 0.7028}, {"ym": "2021-08", "A": -0.01084, "rp": 0.024, "rb": 0.03485, "ic": 0.0817, "n": 30, "herf": 0.04499, "sz": -0.00025, "hc": 0.3333, "ha": 0.3272, "sc": -0.1, "sa2": -0.0772}, {"ym": "2021-09", "A": 0.0173, "rp": 0.02042, "rb": 0.00312, "ic": -0.017, "n": 29, "herf": 0.04585, "sz": 0.00488, "hc": 0.5517, "ha": 0.5813, "sc": 0.1379, "sa2": 0.1616}, {"ym": "2021-10", "A": -0.00525, "rp": -0.03353, "rb": -0.02828, "ic": -0.2379, "n": 31, "herf": 0.04709, "sz": -0.01545, "hc": 0.3793, "ha": 0.3352, "sc": 0.0, "sa2": -0.0382}, {"ym": "2021-11", "A": 0.00217, "rp": 0.02637, "rb": 0.0242, "ic": 0.3399, "n": 30, "herf": 0.04607, "sz": 0.01009, "hc": 0.4483, "ha": 0.4925, "sc": -0.2069, "sa2": -0.1547}, {"ym": "2021-12", "A": 0.01579, "rp": 0.01104, "rb": -0.00475, "ic": 0.1622, "n": 31, "herf": 0.04523, "sz": 0.01499, "hc": 0.6, "ha": 0.6667, "sc": -0.0667, "sa2": -0.0592}, {"ym": "2022-01", "A": -0.00867, "rp": -0.04813, "rb": -0.03946, "ic": 0.0509, "n": 31, "herf": 0.04566, "sz": 0.00566, "hc": 0.4, "ha": 0.3891, "sc": 0.3333, "sa2": 0.3588}, {"ym": "2022-02", "A": -0.00922, "rp": 0.0322, "rb": 0.04143, "ic": 0.0857, "n": 31, "herf": 0.04515, "sz": -0.00374, "hc": 0.3333, "ha": 0.347, "sc": 0.0667, "sa2": 0.1218}, {"ym": "2022-03", "A": -0.0083, "rp": -0.01543, "rb": -0.00713, "ic": -0.2595, "n": 31, "herf": 0.04475, "sz": -0.00875, "hc": 0.6, "ha": 0.5688, "sc": -0.3, "sa2": -0.363}, {"ym": "2022-04", "A": 0.00426, "rp": -0.03799, "rb": -0.04225, "ic": 0.3209, "n": 31, "herf": 0.04395, "sz": 0.00823, "hc": 0.5667, "ha": 0.6174, "sc": 0.2667, "sa2": 0.3213}, {"ym": "2022-05", "A": 0.00441, "rp": -0.04607, "rb": -0.05047, "ic": 0.5349, "n": 31, "herf": 0.04449, "sz": 0.01592, "hc": 0.4333, "ha": 0.5151, "sc": -0.1, "sa2": -0.026}, {"ym": "2022-06", "A": 0.00013, "rp": 0.09743, "rb": 0.0973, "ic": -0.075, "n": 31, "herf": 0.04425, "sz": -0.00562, "hc": 0.4667, "ha": 0.4526, "sc": 0.1, "sa2": 0.1011}, {"ym": "2022-07", "A": -0.00989, "rp": 0.03695, "rb": 0.04683, "ic": 0.1978, "n": 31, "herf": 0.04419, "sz": 0.00462, "hc": 0.4, "ha": 0.4435, "sc": -0.2667, "sa2": -0.2073}, {"ym": "2022-08", "A": 0.01294, "rp": -0.01912, "rb": -0.03205, "ic": -0.1713, "n": 31, "herf": 0.04321, "sz": -0.00679, "hc": 0.6333, "ha": 0.6149, "sc": 0.0667, "sa2": 0.0143}, {"ym": "2022-09", "A": 0.00829, "rp": 0.04921, "rb": 0.04092, "ic": 0.475, "n": 31, "herf": 0.04238, "sz": 0.01286, "hc": 0.5333, "ha": 0.654, "sc": 0.3, "sa2": 0.3989}, {"ym": "2022-10", "A": -0.01593, "rp": 0.0183, "rb": 0.03423, "ic": 0.2214, "n": 31, "herf": 0.04244, "sz": 0.00932, "hc": 0.3667, "ha": 0.4533, "sc": -0.2333, "sa2": -0.171}, {"ym": "2022-11", "A": 0.00376, "rp": -0.02742, "rb": -0.03118, "ic": -0.2323, "n": 31, "herf": 0.04278, "sz": -0.00377, "hc": 0.4667, "ha": 0.4414, "sc": -0.0333, "sa2": -0.1018}, {"ym": "2022-12", "A": 0.0092, "rp": -0.02385, "rb": -0.03305, "ic": -0.0111, "n": 31, "herf": 0.04147, "sz": -0.00328, "hc": 0.5333, "ha": 0.5172, "sc": 0.0, "sa2": -0.0302}, {"ym": "2023-01", "A": 0.01443, "rp": -0.0127, "rb": -0.02713, "ic": -0.1462, "n": 31, "herf": 0.04177, "sz": -0.00184, "hc": 0.5333, "ha": 0.5257, "sc": 0.3333, "sa2": 0.2874}, {"ym": "2023-02", "A": -0.00642, "rp": -0.00362, "rb": 0.0028, "ic": 0.3535, "n": 31, "herf": 0.04168, "sz": 0.00583, "hc": 0.5, "ha": 0.5725, "sc": 0.0333, "sa2": 0.0638}, {"ym": "2023-03", "A": -0.01427, "rp": 0.03148, "rb": 0.04575, "ic": -0.325, "n": 31, "herf": 0.04177, "sz": -0.00632, "hc": 0.5, "ha": 0.4983, "sc": -0.2667, "sa2": -0.2826}, {"ym": "2023-04", "A": -0.00318, "rp": 0.03464, "rb": 0.03782, "ic": -0.3235, "n": 31, "herf": 0.04128, "sz": -0.00921, "hc": 0.5667, "ha": 0.4791, "sc": -0.0333, "sa2": -0.1119}, {"ym": "2023-05", "A": -0.00158, "rp": 0.04194, "rb": 0.04351, "ic": 0.0505, "n": 31, "herf": 0.03976, "sz": -0.00414, "hc": 0.4667, "ha": 0.4798, "sc": -0.1333, "sa2": -0.1748}, {"ym": "2023-06", "A": -0.00322, "rp": 0.0361, "rb": 0.03932, "ic": 0.117, "n": 31, "herf": 0.04243, "sz": -0.00179, "hc": 0.3667, "ha": 0.3926, "sc": -0.2333, "sa2": -0.2619}, {"ym": "2023-07", "A": 0.00901, "rp": 0.00297, "rb": -0.00604, "ic": -0.1685, "n": 31, "herf": 0.04147, "sz": -0.00783, "hc": 0.5172, "ha": 0.4838, "sc": -0.3448, "sa2": -0.4201}, {"ym": "2023-08", "A": -0.01036, "rp": 0.01157, "rb": 0.02193, "ic": 0.19, "n": 31, "herf": 0.04109, "sz": 0.00061, "hc": 0.4, "ha": 0.372, "sc": -0.0333, "sa2": -0.0067}, {"ym": "2023-09", "A": 0.00128, "rp": -0.02647, "rb": -0.02774, "ic": -0.3177, "n": 31, "herf": 0.04093, "sz": -0.00428, "hc": 0.5, "ha": 0.4171, "sc": -0.0333, "sa2": -0.0398}, {"ym": "2023-10", "A": 0.00681, "rp": 0.07832, "rb": 0.07151, "ic": -0.1362, "n": 30, "herf": 0.04029, "sz": -0.00607, "hc": 0.5333, "ha": 0.48, "sc": 0.0333, "sa2": 0.0296}, {"ym": "2023-11", "A": -0.01163, "rp": 0.0685, "rb": 0.08013, "ic": 0.1831, "n": 30, "herf": 0.03893, "sz": 0.00426, "hc": 0.4, "ha": 0.4311, "sc": 0.0333, "sa2": 0.0453}, {"ym": "2023-12", "A": -0.00809, "rp": 0.01142, "rb": 0.01951, "ic": 0.0839, "n": 30, "herf": 0.03969, "sz": -0.00278, "hc": 0.4667, "ha": 0.4712, "sc": -0.3, "sa2": -0.2815}, {"ym": "2024-01", "A": 0.00205, "rp": 0.01779, "rb": 0.01574, "ic": 0.2183, "n": 30, "herf": 0.03945, "sz": 0.00421, "hc": 0.4, "ha": 0.4191, "sc": 0.2, "sa2": 0.246}, {"ym": "2024-02", "A": 0.0115, "rp": 0.01988, "rb": 0.00838, "ic": 0.1582, "n": 30, "herf": 0.03888, "sz": 0.00195, "hc": 0.5, "ha": 0.5436, "sc": 0.5333, "sa2": 0.5908}, {"ym": "2024-03", "A": -0.00137, "rp": 0.03528, "rb": 0.03665, "ic": -0.0325, "n": 30, "herf": 0.03986, "sz": 0.00012, "hc": 0.5, "ha": 0.5222, "sc": -0.4667, "sa2": -0.4546}, {"ym": "2024-04", "A": 0.00779, "rp": 0.01511, "rb": 0.00731, "ic": -0.1482, "n": 30, "herf": 0.03999, "sz": -0.00293, "hc": 0.4333, "ha": 0.4086, "sc": 0.3, "sa2": 0.2397}, {"ym": "2024-05", "A": 0.0092, "rp": 0.07971, "rb": 0.07051, "ic": -0.1809, "n": 30, "herf": 0.03811, "sz": -0.00474, "hc": 0.5667, "ha": 0.5267, "sc": 0.0333, "sa2": 0.0033}, {"ym": "2024-06", "A": 0.00141, "rp": 0.04532, "rb": 0.04391, "ic": -0.205, "n": 30, "herf": 0.03807, "sz": -0.00524, "hc": 0.5, "ha": 0.4384, "sc": -0.0333, "sa2": -0.0779}, {"ym": "2024-07", "A": -0.00287, "rp": 0.00748, "rb": 0.01036, "ic": 0.16, "n": 30, "herf": 0.03798, "sz": 0.00179, "hc": 0.4333, "ha": 0.4557, "sc": -0.0333, "sa2": -0.0054}, {"ym": "2024-08", "A": 0.00714, "rp": 0.02881, "rb": 0.02167, "ic": 0.2303, "n": 29, "herf": 0.03808, "sz": 0.00493, "hc": 0.5172, "ha": 0.5797, "sc": 0.2069, "sa2": 0.2452}, {"ym": "2024-09", "A": -0.00378, "rp": -0.0673, "rb": -0.06352, "ic": 0.2343, "n": 29, "herf": 0.03815, "sz": 0.00415, "hc": 0.4483, "ha": 0.4941, "sc": -0.069, "sa2": -0.0382}, {"ym": "2024-10", "A": 0.0109, "rp": 0.01136, "rb": 0.00046, "ic": -0.0234, "n": 30, "herf": 0.03828, "sz": 0.00114, "hc": 0.5667, "ha": 0.5846, "sc": 0.2, "sa2": 0.1966}, {"ym": "2024-11", "A": -0.01006, "rp": -0.02371, "rb": -0.01366, "ic": 0.2118, "n": 29, "herf": 0.03936, "sz": 0.00266, "hc": 0.3448, "ha": 0.3783, "sc": -0.0345, "sa2": -0.0225}, {"ym": "2024-12", "A": 0.0009, "rp": -0.03381, "rb": -0.0347, "ic": 0.15, "n": 30, "herf": 0.03878, "sz": -0.00088, "hc": 0.5, "ha": 0.554, "sc": 0.3667, "sa2": 0.4392}, {"ym": "2025-01", "A": 0.01171, "rp": -0.06615, "rb": -0.07786, "ic": 0.1069, "n": 29, "herf": 0.0392, "sz": 0.00428, "hc": 0.5172, "ha": 0.5276, "sc": 0.4828, "sa2": 0.5253}, {"ym": "2025-02", "A": -0.00733, "rp": 0.0662, "rb": 0.07353, "ic": -0.1957, "n": 28, "herf": 0.04136, "sz": -0.00437, "hc": 0.5714, "ha": 0.5464, "sc": 0.1429, "sa2": 0.0565}, {"ym": "2025-03", "A": -0.00154, "rp": 0.03097, "rb": 0.03251, "ic": 0.3123, "n": 28, "herf": 0.04144, "sz": 0.00824, "hc": 0.5, "ha": 0.586, "sc": -0.0714, "sa2": -0.0379}, {"ym": "2025-04", "A": -0.00624, "rp": 0.03029, "rb": 0.03652, "ic": -0.2792, "n": 28, "herf": 0.0423, "sz": -0.01157, "hc": 0.4286, "ha": 0.3527, "sc": -0.3571, "sa2": -0.4832}, {"ym": "2025-05", "A": 0.01235, "rp": 0.05002, "rb": 0.03767, "ic": 0.0264, "n": 29, "herf": 0.04096, "sz": -0.00084, "hc": 0.5517, "ha": 0.5734, "sc": 0.1724, "sa2": 0.1742}, {"ym": "2025-06", "A": 0.01504, "rp": -0.01323, "rb": -0.02827, "ic": -0.0739, "n": 29, "herf": 0.04048, "sz": 0.00028, "hc": 0.5862, "ha": 0.5676, "sc": -0.0345, "sa2": -0.0587}, {"ym": "2025-07", "A": 0.01422, "rp": -0.00395, "rb": -0.01817, "ic": -0.0552, "n": 29, "herf": 0.04069, "sz": -0.00433, "hc": 0.5172, "ha": 0.4923, "sc": 0.3103, "sa2": 0.2943}, {"ym": "2025-08", "A": 0.00372, "rp": 0.01604, "rb": 0.01232, "ic": 0.1916, "n": 28, "herf": 0.04138, "sz": 0.00115, "hc": 0.4643, "ha": 0.4452, "sc": 0.1786, "sa2": 0.2005}, {"ym": "2025-09", "A": 0.00326, "rp": 0.04692, "rb": 0.04366, "ic": -0.2173, "n": 28, "herf": 0.04177, "sz": -0.00801, "hc": 0.4643, "ha": 0.4261, "sc": 0.3214, "sa2": 0.2896}, {"ym": "2025-10", "A": 0.00832, "rp": 0.01828, "rb": 0.00996, "ic": 0.0205, "n": 28, "herf": 0.04271, "sz": 0.00058, "hc": 0.5926, "ha": 0.6282, "sc": 0.5926, "sa2": 0.6175}, {"ym": "2025-11", "A": -0.00742, "rp": -0.00999, "rb": -0.00257, "ic": -0.2036, "n": 28, "herf": 0.04279, "sz": -0.00061, "hc": 0.3571, "ha": 0.2987, "sc": 0.25, "sa2": 0.21}, {"ym": "2025-12", "A": 0.01943, "rp": -0.0133, "rb": -0.03273, "ic": 0.0974, "n": 28, "herf": 0.04247, "sz": 0.00114, "hc": 0.4643, "ha": 0.4832, "sc": 0.3929, "sa2": 0.3899}, {"ym": "2026-01", "A": 0.00596, "rp": 0.01048, "rb": 0.00452, "ic": -0.2326, "n": 28, "herf": 0.04231, "sz": -0.00796, "hc": 0.6071, "ha": 0.565, "sc": 0.1071, "sa2": 0.0772}, {"ym": "2026-02", "A": -0.00548, "rp": -0.11913, "rb": -0.11365, "ic": -0.2631, "n": 29, "herf": 0.04162, "sz": -0.00915, "hc": 0.4828, "ha": 0.4415, "sc": 0.3793, "sa2": 0.3202}, {"ym": "2026-03", "A": -0.01055, "rp": 0.0947, "rb": 0.10525, "ic": -0.3038, "n": 28, "herf": 0.04041, "sz": -0.00563, "hc": 0.2857, "ha": 0.2265, "sc": -0.6786, "sa2": -0.741}, {"ym": "2026-04", "A": 0.00344, "rp": 0.00331, "rb": -0.00013, "ic": -0.3638, "n": 28, "herf": 0.03981, "sz": -0.00916, "hc": 0.5357, "ha": 0.4728, "sc": 0.0714, "sa2": 0.0127}, {"ym": "2026-05", "A": 0.01479, "rp": 0.03747, "rb": 0.02269, "ic": 0.2621, "n": 29, "herf": 0.03802, "sz": 0.00337, "hc": 0.6207, "ha": 0.6785, "sc": -0.0345, "sa2": -0.0264}], "portfolio": {"asof": "2026-05-31", "n_equity": 29, "equity_pct_fund": 96.3, "asset_alloc": {"Equity": 96.3}, "sector_cover": 98.1, "sector_now": [{"sector": "Financial Services", "pct": 29.8}, {"sector": "Capital Goods", "pct": 13.9}, {"sector": "Healthcare", "pct": 9.2}, {"sector": "Automobile and Auto Components", "pct": 6.2}, {"sector": "Fast Moving Consumer Goods", "pct": 5.0}, {"sector": "Telecommunication", "pct": 5.0}, {"sector": "Consumer Services", "pct": 4.4}, {"sector": "Information Technology", "pct": 4.4}, {"sector": "Oil Gas & Consumable Fuels", "pct": 4.2}, {"sector": "Power", "pct": 3.5}, {"sector": "Construction Materials", "pct": 2.9}, {"sector": "Construction", "pct": 2.8}, {"sector": "Services", "pct": 2.7}, {"sector": "Chemicals", "pct": 2.3}, {"sector": "Consumer Durables", "pct": 1.9}, {"sector": "Unclassified", "pct": 1.9}], "top_holdings": [{"name": "HDFC Bank Ltd", "symbol": "HDFCBANK", "pct": 5.8, "sector": "Financial Services", "vst_id": "VST02887"}, {"name": "ICICI Bank Ltd", "symbol": "ICICIBANK", "pct": 5.51, "sector": "Financial Services", "vst_id": "VST02975"}, {"name": "Bharti Airtel Ltd", "symbol": "BHARTIARTL", "pct": 4.79, "sector": "Telecommunication", "vst_id": "VST02300"}, {"name": "Shriram Finance Ltd", "symbol": "SHRIRAMFIN", "pct": 4.66, "sector": "Financial Services", "vst_id": "VST04130"}, {"name": "State Bank of India", "symbol": "SBIN", "pct": 4.39, "sector": "Financial Services", "vst_id": "VST03972"}, {"name": "Eternal Ltd", "symbol": "ETERNAL", "pct": 4.2, "sector": "Consumer Services", "vst_id": "VST01377"}, {"name": "Reliance Industries Ltd", "symbol": "RELIANCE", "pct": 4.05, "sector": "Oil Gas & Consumable Fuels", "vst_id": "VST03868"}, {"name": "KEI Industries Ltd", "symbol": "KEI", "pct": 3.91, "sector": "Capital Goods", "vst_id": "VST03217"}, {"name": "Fortis Healthcare Ltd", "symbol": "FORTIS", "pct": 3.87, "sector": "Healthcare", "vst_id": "VST02697"}, {"name": "Bharat Electronics Ltd", "symbol": "BEL", "pct": 3.6, "sector": "Capital Goods", "vst_id": "VST02277"}, {"name": "NTPC Ltd", "symbol": "NTPC", "pct": 3.35, "sector": "Power", "vst_id": "VST03610"}, {"name": "Radico Khaitan Ltd", "symbol": "RADICO", "pct": 3.08, "sector": "Fast Moving Consumer Goods", "vst_id": "VST03810"}, {"name": "GE Vernova T&D India Ltd", "symbol": "GVT&D", "pct": 3.04, "sector": "Capital Goods", "vst_id": "VST02145"}, {"name": "Axis Bank Ltd", "symbol": "AXISBANK", "pct": 3.03, "sector": "Financial Services", "vst_id": "VST02217"}, {"name": "Maruti Suzuki India Ltd", "symbol": "MARUTI", "pct": 3.0, "sector": "Automobile and Auto Components", "vst_id": "VST03398"}], "by_sector": [{"sector": "Financial Services", "pct": 28.68, "names": [{"name": "HDFC Bank Ltd", "symbol": "HDFCBANK", "pct": 5.8}, {"name": "ICICI Bank Ltd", "symbol": "ICICIBANK", "pct": 5.51}, {"name": "Shriram Finance Ltd", "symbol": "SHRIRAMFIN", "pct": 4.66}, {"name": "State Bank of India", "symbol": "SBIN", "pct": 4.39}, {"name": "Axis Bank Ltd", "symbol": "AXISBANK", "pct": 3.03}, {"name": "BSE Ltd", "symbol": "BSE", "pct": 2.84}, {"name": "Poonawalla Fincorp Ltd", "symbol": "POONAWALLA", "pct": 2.45}]}, {"sector": "Capital Goods", "pct": 13.35, "names": [{"name": "KEI Industries Ltd", "symbol": "KEI", "pct": 3.91}, {"name": "Bharat Electronics Ltd", "symbol": "BEL", "pct": 3.6}, {"name": "GE Vernova T&D India Ltd", "symbol": "GVT&D", "pct": 3.04}, {"name": "Astra Microwave Products Ltd", "symbol": "ASTRAMICRO", "pct": 2.8}]}, {"sector": "Healthcare", "pct": 8.89, "names": [{"name": "Fortis Healthcare Ltd", "symbol": "FORTIS", "pct": 3.87}, {"name": "Divis Laboratories Ltd", "symbol": "DIVISLAB", "pct": 2.63}, {"name": "Krishna Institute of Medical Sciences Ltd", "symbol": "KIMS", "pct": 2.39}]}, {"sector": "Automobile and Auto Components", "pct": 5.95, "names": [{"name": "Maruti Suzuki India Ltd", "symbol": "MARUTI", "pct": 3.0}, {"name": "Hero MotoCorp Ltd", "symbol": "HEROMOTOCO", "pct": 2.95}]}, {"sector": "Fast Moving Consumer Goods", "pct": 4.81, "names": [{"name": "Radico Khaitan Ltd", "symbol": "RADICO", "pct": 3.08}, {"name": "Godrej Consumer Products Ltd", "symbol": "GODREJCP", "pct": 1.73}]}, {"sector": "Telecommunication", "pct": 4.79, "names": [{"name": "Bharti Airtel Ltd", "symbol": "BHARTIARTL", "pct": 4.79}]}, {"sector": "Consumer Services", "pct": 4.2, "names": [{"name": "Eternal Ltd", "symbol": "ETERNAL", "pct": 4.2}]}, {"sector": "Information Technology", "pct": 4.19, "names": [{"name": "Tech Mahindra Ltd", "symbol": "TECHM", "pct": 2.56}, {"name": "Persistent Systems Ltd", "symbol": "PERSISTENT", "pct": 1.63}]}, {"sector": "Oil Gas & Consumable Fuels", "pct": 4.05, "names": [{"name": "Reliance Industries Ltd", "symbol": "RELIANCE", "pct": 4.05}]}, {"sector": "Power", "pct": 3.35, "names": [{"name": "NTPC Ltd", "symbol": "NTPC", "pct": 3.35}]}, {"sector": "Construction Materials", "pct": 2.82, "names": [{"name": "UltraTech Cement Ltd", "symbol": "ULTRACEMCO", "pct": 2.82}]}, {"sector": "Construction", "pct": 2.65, "names": [{"name": "Larsen & Toubro Ltd", "symbol": "LT", "pct": 2.65}]}, {"sector": "Services", "pct": 2.64, "names": [{"name": "Interglobe Aviation Ltd", "symbol": "INDIGO", "pct": 2.64}]}, {"sector": "Chemicals", "pct": 2.2, "names": [{"name": "SRF Ltd", "symbol": "SRF", "pct": 2.2}]}, {"sector": "Consumer Durables", "pct": 1.87, "names": [{"name": "Blue Star Ltd", "symbol": "BLUESTARCO", "pct": 1.87}]}, {"sector": "Unclassified", "pct": 1.85, "names": [{"name": "ICICI Prudential Asset Management Co Ltd", "symbol": null, "pct": 1.85}]}], "rotation": {"dates": ["2019-09", "2020-03", "2020-09", "2021-03", "2021-09", "2022-03", "2022-09", "2023-03", "2023-09", "2024-03", "2024-09", "2025-03", "2025-09", "2026-03", "2026-05"], "sectors": ["Financial Services", "Information Technology", "Automobile and Auto Components", "Capital Goods", "Oil Gas & Consumable Fuels", "Healthcare", "Fast Moving Consumer Goods", "Consumer Durables", "Construction Materials", "Unclassified", "Other"], "matrix": [[36.3, 34.6, 26.0, 32.1, 32.8, 30.7, 31.0, 28.3, 27.9, 24.4, 21.7, 28.8, 27.3, 30.2, 29.8], [9.0, 9.9, 15.7, 11.7, 12.3, 10.8, 8.4, 9.5, 11.3, 9.3, 11.4, 10.2, 9.3, 7.5, 4.4], [2.7, 2.6, 6.1, 6.3, 5.5, 6.0, 10.3, 10.8, 14.7, 14.7, 11.0, 6.7, 8.2, 7.2, 6.2], [4.9, 2.6, 3.1, 5.1, 6.0, 7.0, 8.3, 9.6, 6.6, 6.6, 6.9, 5.6, 10.6, 11.3, 13.9], [9.6, 10.0, 10.2, 6.6, 6.9, 7.4, 6.0, 4.7, 4.4, 7.7, 7.3, 7.1, 5.0, 4.8, 4.2], [1.9, 2.4, 5.4, 2.8, 3.6, 6.1, 6.0, 6.4, 5.2, 8.8, 7.5, 7.5, 5.4, 6.2, 9.2], [7.9, 7.1, 7.0, 6.8, 2.2, 2.4, 3.1, 5.7, 5.4, 5.1, 5.2, 2.4, 2.2, 4.7, 5.0], [2.8, 1.8, 2.1, 5.6, 8.6, 9.8, 8.9, 6.0, 4.7, 2.0, 5.7, 4.4, 2.4, 2.2, 1.9], [4.4, 6.5, 6.6, 7.6, 6.1, 3.8, 2.8, 3.8, 3.9, 4.0, 3.0, 3.3, 3.1, 3.1, 2.9], [6.9, 5.4, 4.9, 4.2, 1.9, 2.0, 1.9, 2.1, 1.6, 0.0, 0.0, 0.0, 0.0, 1.7, 1.9], [13.7, 17.3, 13.0, 11.1, 14.2, 14.2, 13.4, 13.0, 14.5, 17.5, 20.5, 23.9, 26.5, 21.3, 20.6]]}, "conc_ts": [{"ym": "2019-09", "top10": 55.8, "n": 30}, {"ym": "2020-03", "top10": 55.3, "n": 30}, {"ym": "2020-09", "top10": 54.0, "n": 29}, {"ym": "2021-03", "top10": 54.2, "n": 30}, {"ym": "2021-09", "top10": 56.4, "n": 29}, {"ym": "2022-03", "top10": 54.3, "n": 31}, {"ym": "2022-09", "top10": 52.0, "n": 31}, {"ym": "2023-03", "top10": 52.2, "n": 31}, {"ym": "2023-09", "top10": 50.1, "n": 31}, {"ym": "2024-03", "top10": 49.6, "n": 30}, {"ym": "2024-09", "top10": 47.3, "n": 29}, {"ym": "2025-03", "top10": 50.2, "n": 28}, {"ym": "2025-09", "top10": 50.7, "n": 28}, {"ym": "2026-03", "top10": 49.2, "n": 28}, {"ym": "2026-05", "top10": 46.5, "n": 29}]}}