{"navindia_code": "44771", "scheme_name": "Bandhan Innovation Fund - Regular (G)", "amc": "Bandhan Mutual Fund", "sebi_category": "Sectoral / Thematic", "benchmark": "NIFTY 500", "n_months": 26, "years": 2.2, "gappy": false, "is_thematic": true, "is_hybrid": false, "excess_cagr": 0.134, "cagr_paper": 0.1904, "cagr_bench": 0.0564, "info_ratio": 1.4414, "t_stat": 2.1218, "years_needed": 1.8489, "tracking_error": 0.0892, "ic_mean": -0.0044, "ic_t": -0.1589, "sizing_edge_cum": -0.057, "hit_rate_monthly": 0.7308, "mag_hit": 0.7303, "slugging": 1.0, "avg_win": 0.02324, "avg_loss": -0.02329, "port_hit_cnt": 0.4961, "port_hit_aum": 0.4922, "port_slug_cnt": 0.0953, "port_slug_aum": 0.0941, "herfindahl": 0.021, "herfindahl_avg": 0.0198, "eff_n": 47.6, "avg_names": 71.2, "boot_meanA_lo": -0.00035, "boot_meanA_hi": 0.0218, "boot_p_positive": 0.9665, "verdict": "skilled", "verdict_why": "+13.4%/yr gross, t=2.1, bootstrap 97% (mixed-source) — but vs the broad market, so largely a sector bet, not pure selection", "basis": "GROSS holdings-implied total-return excess vs the SEBI-category benchmark (pre-cost, pre-cash-drag, pre-factor-deflation); domestic equity sleeve only, month-end snapshots. ‘Holding-rank IC’ is a cap-tilt-contaminated proxy, not pure active-weight selection (needs point-in-time benchmark weights).", "ts": [{"ym": "2024-04", "A": 0.0202, "rp": 0.02751, "rb": 0.00731, "ic": 0.1421, "n": 43, "herf": 0.02943, "sz": -8e-05, "hc": 0.5349, "ha": 0.5367, "sc": 0.3256, "sa2": 0.3777}, {"ym": "2024-05", "A": 0.01641, "rp": 0.08693, "rb": 0.07051, "ic": -0.1028, "n": 62, "herf": 0.01931, "sz": -0.00659, "hc": 0.5574, "ha": 0.5309, "sc": -0.0656, "sa2": -0.1184}, {"ym": "2024-06", "A": 0.04182, "rp": 0.08573, "rb": 0.04391, "ic": -0.237, "n": 64, "herf": 0.01861, "sz": -0.00619, "hc": 0.6508, "ha": 0.6269, "sc": 0.1429, "sa2": 0.1075}, {"ym": "2024-07", "A": 0.03905, "rp": 0.04941, "rb": 0.01036, "ic": 0.1745, "n": 72, "herf": 0.01745, "sz": 0.00443, "hc": 0.5775, "ha": 0.5988, "sc": 0.169, "sa2": 0.2311}, {"ym": "2024-08", "A": 0.02589, "rp": 0.04756, "rb": 0.02167, "ic": -0.0357, "n": 74, "herf": 0.0167, "sz": -0.00032, "hc": 0.5479, "ha": 0.5633, "sc": 0.3288, "sa2": 0.3322}, {"ym": "2024-09", "A": 0.02353, "rp": -0.03999, "rb": -0.06352, "ic": -0.0143, "n": 79, "herf": 0.01617, "sz": -0.00278, "hc": 0.5128, "ha": 0.5079, "sc": 0.0641, "sa2": 0.0309}, {"ym": "2024-10", "A": 0.01961, "rp": 0.02007, "rb": 0.00046, "ic": 0.2546, "n": 76, "herf": 0.01667, "sz": 0.00694, "hc": 0.48, "ha": 0.5294, "sc": 0.0267, "sa2": 0.1149}, {"ym": "2024-11", "A": 0.03604, "rp": 0.02239, "rb": -0.01366, "ic": 0.1523, "n": 75, "herf": 0.01757, "sz": 0.00321, "hc": 0.5676, "ha": 0.6536, "sc": 0.0676, "sa2": 0.1401}, {"ym": "2024-12", "A": -0.07027, "rp": -0.10497, "rb": -0.0347, "ic": -0.206, "n": 78, "herf": 0.01732, "sz": -0.00608, "hc": 0.2338, "ha": 0.2197, "sc": -0.1039, "sa2": -0.1512}, {"ym": "2025-01", "A": -0.0193, "rp": -0.09716, "rb": -0.07786, "ic": 0.1908, "n": 72, "herf": 0.0189, "sz": 0.01629, "hc": 0.2958, "ha": 0.33, "sc": 0.1549, "sa2": 0.2642}, {"ym": "2025-02", "A": 0.01839, "rp": 0.09191, "rb": 0.07353, "ic": -0.2161, "n": 69, "herf": 0.02061, "sz": -0.0096, "hc": 0.5441, "ha": 0.5173, "sc": 0.2794, "sa2": 0.1961}, {"ym": "2025-03", "A": -0.02129, "rp": 0.01122, "rb": 0.03251, "ic": -0.2064, "n": 70, "herf": 0.02026, "sz": -0.00685, "hc": 0.4058, "ha": 0.3686, "sc": -0.0725, "sa2": -0.1136}, {"ym": "2025-04", "A": 0.02117, "rp": 0.0577, "rb": 0.03652, "ic": -0.023, "n": 71, "herf": 0.01986, "sz": -0.01043, "hc": 0.5714, "ha": 0.4792, "sc": -0.1, "sa2": -0.1461}, {"ym": "2025-05", "A": 0.00563, "rp": 0.0433, "rb": 0.03767, "ic": 0.0582, "n": 76, "herf": 0.01783, "sz": 0.00351, "hc": 0.48, "ha": 0.5195, "sc": 0.08, "sa2": 0.128}, {"ym": "2025-06", "A": 0.03709, "rp": 0.00882, "rb": -0.02827, "ic": 0.0171, "n": 76, "herf": 0.01851, "sz": 0.00556, "hc": 0.5467, "ha": 0.5863, "sc": 0.0, "sa2": 0.0271}, {"ym": "2025-07", "A": 0.00952, "rp": -0.00864, "rb": -0.01817, "ic": -0.1266, "n": 74, "herf": 0.01955, "sz": 0.00205, "hc": 0.4795, "ha": 0.4816, "sc": 0.1781, "sa2": 0.2008}, {"ym": "2025-08", "A": -0.00014, "rp": 0.01217, "rb": 0.01232, "ic": -0.0338, "n": 75, "herf": 0.01995, "sz": -0.0049, "hc": 0.473, "ha": 0.4712, "sc": 0.0541, "sa2": 0.0196}, {"ym": "2025-09", "A": 0.00987, "rp": 0.05353, "rb": 0.04366, "ic": 0.0411, "n": 75, "herf": 0.02002, "sz": -0.00044, "hc": 0.527, "ha": 0.5334, "sc": 0.2027, "sa2": 0.2492}, {"ym": "2025-10", "A": -0.01894, "rp": -0.00898, "rb": 0.00996, "ic": 0.0454, "n": 74, "herf": 0.0208, "sz": 0.00051, "hc": 0.3919, "ha": 0.4169, "sc": 0.2568, "sa2": 0.3161}, {"ym": "2025-11", "A": -0.01313, "rp": -0.0157, "rb": -0.00257, "ic": 0.1017, "n": 73, "herf": 0.02156, "sz": 0.00305, "hc": 0.3288, "ha": 0.2952, "sc": 0.0959, "sa2": 0.1234}, {"ym": "2025-12", "A": -0.01997, "rp": -0.0527, "rb": -0.03273, "ic": 0.1264, "n": 68, "herf": 0.02197, "sz": 0.00453, "hc": 0.3382, "ha": 0.3358, "sc": 0.0294, "sa2": 0.0298}, {"ym": "2026-01", "A": 0.01975, "rp": 0.02427, "rb": 0.00452, "ic": -0.0447, "n": 68, "herf": 0.02183, "sz": -0.01249, "hc": 0.6029, "ha": 0.5587, "sc": 0.2059, "sa2": 0.1032}, {"ym": "2026-02", "A": 0.01156, "rp": -0.10209, "rb": -0.11365, "ic": 0.0354, "n": 69, "herf": 0.02127, "sz": 0.00084, "hc": 0.5507, "ha": 0.5269, "sc": 0.2754, "sa2": 0.3266}, {"ym": "2026-03", "A": 0.04196, "rp": 0.14721, "rb": 0.10525, "ic": -0.2155, "n": 71, "herf": 0.02197, "sz": -0.02284, "hc": 0.5775, "ha": 0.4805, "sc": -0.2535, "sa2": -0.4024}, {"ym": "2026-04", "A": 0.03542, "rp": 0.03529, "rb": -0.00013, "ic": 0.1252, "n": 73, "herf": 0.02071, "sz": 0.00127, "hc": 0.5753, "ha": 0.6114, "sc": 0.0822, "sa2": 0.066}, {"ym": "2026-05", "A": 0.00861, "rp": 0.0313, "rb": 0.02269, "ic": -0.1182, "n": 73, "herf": 0.021, "sz": -0.00841, "hc": 0.5479, "ha": 0.5184, "sc": 0.0548, "sa2": -0.005}], "portfolio": {"asof": "2026-05-31", "n_equity": 73, "equity_pct_fund": 98.2, "asset_alloc": {"Equity": 98.2}, "sector_cover": 86.2, "sector_now": [{"sector": "Financial Services", "pct": 18.5}, {"sector": "Unclassified", "pct": 13.8}, {"sector": "Consumer Services", "pct": 10.0}, {"sector": "Healthcare", "pct": 8.8}, {"sector": "Automobile and Auto Components", "pct": 8.7}, {"sector": "Capital Goods", "pct": 8.2}, {"sector": "Fast Moving Consumer Goods", "pct": 5.8}, {"sector": "Information Technology", "pct": 4.9}, {"sector": "Consumer Durables", "pct": 4.1}, {"sector": "Telecommunication", "pct": 2.6}, {"sector": "Realty", "pct": 2.4}, {"sector": "Chemicals", "pct": 2.3}, {"sector": "Oil Gas & Consumable Fuels", "pct": 2.3}, {"sector": "Services", "pct": 2.3}, {"sector": "Power", "pct": 1.7}, {"sector": "Media Entertainment & Publication", "pct": 1.2}, {"sector": "Metals & Mining", "pct": 0.8}, {"sector": "Diversified", "pct": 0.7}, {"sector": "Construction", "pct": 0.6}, {"sector": "Textiles", "pct": 0.3}], "top_holdings": [{"name": "Eternal Ltd", "symbol": "ETERNAL", "pct": 4.74, "sector": "Consumer Services", "vst_id": "VST01377"}, {"name": "One 97 Communications Ltd", "symbol": "PAYTM", "pct": 4.2, "sector": "Financial Services", "vst_id": "VST01667"}, {"name": "Astrazeneca Pharma India Ltd", "symbol": "ASTRAZEN", "pct": 3.74, "sector": "Unclassified", "vst_id": "VST02188"}, {"name": "ICICI Bank Ltd", "symbol": "ICICIBANK", "pct": 3.67, "sector": "Financial Services", "vst_id": "VST02975"}, {"name": "Bajaj Finserv Ltd", "symbol": "BAJAJFINSV", "pct": 3.67, "sector": "Financial Services", "vst_id": "VST02229"}, {"name": "Honasa Consumer Ltd", "symbol": "HONASA", "pct": 2.35, "sector": "Fast Moving Consumer Goods", "vst_id": "VST00364"}, {"name": "Varun Beverages Ltd", "symbol": "VBL", "pct": 2.31, "sector": "Fast Moving Consumer Goods", "vst_id": "VST00634"}, {"name": "Jubilant Ingrevia Ltd", "symbol": "JUBLINGREA", "pct": 2.3, "sector": "Chemicals", "vst_id": "VST00298"}, {"name": "Reliance Industries Ltd", "symbol": "RELIANCE", "pct": 2.28, "sector": "Oil Gas & Consumable Fuels", "vst_id": "VST03868"}, {"name": "Coforge Ltd", "symbol": "COFORGE", "pct": 2.28, "sector": "Information Technology", "vst_id": "VST03579"}, {"name": "Mahindra & Mahindra Ltd", "symbol": "M&M", "pct": 2.13, "sector": "Automobile and Auto Components", "vst_id": "VST03341"}, {"name": "MTAR Technologies Ltd", "symbol": "MTARTECH", "pct": 2.02, "sector": "Capital Goods", "vst_id": "VST01503"}, {"name": "GE Vernova T&D India Ltd", "symbol": "GVT&D", "pct": 1.95, "sector": "Capital Goods", "vst_id": "VST02145"}, {"name": "Amber Enterprises India Ltd", "symbol": "AMBER", "pct": 1.75, "sector": "Consumer Durables", "vst_id": "VST00866"}, {"name": "Poonawalla Fincorp Ltd", "symbol": "POONAWALLA", "pct": 1.67, "sector": "Financial Services", "vst_id": "VST03357"}], "by_sector": [{"sector": "Financial Services", "pct": 18.21, "names": [{"name": "One 97 Communications Ltd", "symbol": "PAYTM", "pct": 4.2}, {"name": "ICICI Bank Ltd", "symbol": "ICICIBANK", "pct": 3.67}, {"name": "Bajaj Finserv Ltd", "symbol": "BAJAJFINSV", "pct": 3.67}, {"name": "Poonawalla Fincorp Ltd", "symbol": "POONAWALLA", "pct": 1.67}, {"name": "Cholamandalam Investment & Finance Company Ltd", "symbol": "CHOLAFIN", "pct": 1.27}, {"name": "Max Financial Services Ltd", "symbol": "MFSL", "pct": 0.97}, {"name": "Canara HSBC Life Insurance Company Ltd", "symbol": "CANHLIFE", "pct": 0.94}, {"name": "HDFC Bank Ltd", "symbol": "HDFCBANK", "pct": 0.92}, {"name": "KFin Technologies Ltd", "symbol": "KFINTECH", "pct": 0.9}]}, {"sector": "Unclassified", "pct": 13.58, "names": [{"name": "Astrazeneca Pharma India Ltd", "symbol": "ASTRAZEN", "pct": 3.74}, {"name": "E2E Networks Ltd", "symbol": "E2E", "pct": 1.59}, {"name": "Billionbrains Garage Ventures Ltd", "symbol": null, "pct": 1.54}, {"name": "Vintage Coffee & Beverages Ltd", "symbol": "VINCOFE", "pct": 1.15}, {"name": "Amagi Media Labs Ltd", "symbol": null, "pct": 0.99}, {"name": "Meesho Ltd", "symbol": null, "pct": 0.74}, {"name": "Rashi Peripherals Ltd", "symbol": "RPTECH", "pct": 0.66}, {"name": "Suraksha Diagnostic Ltd", "symbol": "SURAKSHA", "pct": 0.57}, {"name": "Afcom Holdings Ltd", "symbol": null, "pct": 0.45}, {"name": "Vedanta Power Ltd", "symbol": null, "pct": 0.33}, {"name": "Vedanta Aluminium Metal Ltd", "symbol": null, "pct": 0.33}, {"name": "Vedanta Iron & Steel Ltd", "symbol": null, "pct": 0.33}, {"name": "Malco Energy Ltd", "symbol": null, "pct": 0.33}, {"name": "Amir Chand Jagdish Kumar (Exports) Ltd", "symbol": null, "pct": 0.29}, {"name": "Novartis India Ltd", "symbol": "NOVARTIND", "pct": 0.28}, {"name": "Stove Kraft Ltd", "symbol": "STOVEKRAFT", "pct": 0.26}]}, {"sector": "Consumer Services", "pct": 9.79, "names": [{"name": "Eternal Ltd", "symbol": "ETERNAL", "pct": 4.74}, {"name": "Info Edge (India) Ltd", "symbol": "NAUKRI", "pct": 1.27}, {"name": "Trent Ltd", "symbol": "TRENT", "pct": 1.02}, {"name": "Indian Hotels Co Ltd", "symbol": "INDHOTEL", "pct": 0.83}, {"name": "Jubilant Foodworks Ltd", "symbol": "JUBLFOOD", "pct": 0.75}, {"name": "Avenue Supermarts Ltd", "symbol": "DMART", "pct": 0.57}, {"name": "Electronics Mart India Ltd", "symbol": "EMIL", "pct": 0.56}, {"name": "Vedant Fashions Ltd", "symbol": "MANYAVAR", "pct": 0.05}]}, {"sector": "Healthcare", "pct": 8.62, "names": [{"name": "Dr Agarwals Health Care Ltd", "symbol": "AGARWALEYE", "pct": 1.47}, {"name": "Divis Laboratories Ltd", "symbol": "DIVISLAB", "pct": 1.4}, {"name": "Glenmark Pharmaceuticals Ltd", "symbol": "GLENMARK", "pct": 1.17}, {"name": "Sai Life Sciences Ltd", "symbol": "SAILIFE", "pct": 1.06}, {"name": "Jubilant Pharmova Ltd", "symbol": "JUBLPHARMA", "pct": 1.04}, {"name": "Fortis Healthcare Ltd", "symbol": "FORTIS", "pct": 0.96}, {"name": "Torrent Pharmaceuticals Ltd", "symbol": "TORNTPHARM", "pct": 0.77}, {"name": "Jupiter Life Line Hospitals Ltd", "symbol": "JLHL", "pct": 0.42}, {"name": "Cohance Lifesciences Ltd", "symbol": "COHANCE", "pct": 0.33}]}, {"sector": "Automobile and Auto Components", "pct": 8.51, "names": [{"name": "Mahindra & Mahindra Ltd", "symbol": "M&M", "pct": 2.13}, {"name": "Tube Investments of India Ltd", "symbol": "TIINDIA", "pct": 1.39}, {"name": "ZF Commercial Vehicle Control System India Ltd", "symbol": "ZFCVINDIA", "pct": 1.3}, {"name": "Eicher Motors Ltd", "symbol": "EICHERMOT", "pct": 1.2}, {"name": "Ather Energy Ltd", "symbol": "ATHERENERG", "pct": 1.09}, {"name": "Sona BLW Precision Forgings Ltd", "symbol": "SONACOMS", "pct": 0.81}, {"name": "Bajaj Auto Ltd", "symbol": "BAJAJ-AUTO", "pct": 0.59}]}, {"sector": "Capital Goods", "pct": 8.08, "names": [{"name": "MTAR Technologies Ltd", "symbol": "MTARTECH", "pct": 2.02}, {"name": "GE Vernova T&D India Ltd", "symbol": "GVT&D", "pct": 1.95}, {"name": "Bharat Electronics Ltd", "symbol": "BEL", "pct": 1.25}, {"name": "Tega Industries Ltd", "symbol": "TEGA", "pct": 0.93}, {"name": "ABB India Ltd", "symbol": "ABB", "pct": 0.93}, {"name": "Usha Martin Ltd", "symbol": "USHAMART", "pct": 0.5}, {"name": "KRN Heat Exchanger and Refrigeration Ltd", "symbol": "KRN", "pct": 0.5}]}, {"sector": "Fast Moving Consumer Goods", "pct": 5.72, "names": [{"name": "Honasa Consumer Ltd", "symbol": "HONASA", "pct": 2.35}, {"name": "Varun Beverages Ltd", "symbol": "VBL", "pct": 2.31}, {"name": "Tilaknagar Industries Ltd", "symbol": "TI", "pct": 1.06}]}, {"sector": "Information Technology", "pct": 4.78, "names": [{"name": "Coforge Ltd", "symbol": "COFORGE", "pct": 2.28}, {"name": "Affle 3i Ltd", "symbol": "AFFLE", "pct": 1.02}, {"name": "Infosys Ltd", "symbol": "INFY", "pct": 0.94}, {"name": "Tech Mahindra Ltd", "symbol": "TECHM", "pct": 0.54}]}, {"sector": "Consumer Durables", "pct": 4.03, "names": [{"name": "Amber Enterprises India Ltd", "symbol": "AMBER", "pct": 1.75}, {"name": "Thangamayil Jewellery Ltd", "symbol": "THANGAMAYL", "pct": 1.56}, {"name": "Ethos Ltd", "symbol": "ETHOSLTD", "pct": 0.72}]}, {"sector": "Telecommunication", "pct": 2.52, "names": [{"name": "Sterlite Technologies Ltd", "symbol": "STLTECH", "pct": 1.64}, {"name": "Tata Communications Ltd", "symbol": "TATACOMM", "pct": 0.51}, {"name": "Optiemus Infracom Ltd", "symbol": "OPTIEMUS", "pct": 0.37}]}, {"sector": "Realty", "pct": 2.39, "names": [{"name": "Prestige Estates Projects Ltd", "symbol": "PRESTIGE", "pct": 1.37}, {"name": "Godrej Properties Ltd", "symbol": "GODREJPROP", "pct": 1.02}]}, {"sector": "Chemicals", "pct": 2.3, "names": [{"name": "Jubilant Ingrevia Ltd", "symbol": "JUBLINGREA", "pct": 2.3}]}, {"sector": "Oil Gas & Consumable Fuels", "pct": 2.28, "names": [{"name": "Reliance Industries Ltd", "symbol": "RELIANCE", "pct": 2.28}]}, {"sector": "Services", "pct": 2.25, "names": [{"name": "Adani Ports & Special Economic Zone Ltd", "symbol": "ADANIPORTS", "pct": 1.43}, {"name": "Blackbuck Ltd", "symbol": "BLACKBUCK", "pct": 0.58}, {"name": "Inox Green Energy Services Ltd", "symbol": "INOXGREEN", "pct": 0.24}]}, {"sector": "Power", "pct": 1.64, "names": [{"name": "NTPC Ltd", "symbol": "NTPC", "pct": 1.64}]}, {"sector": "Media Entertainment & Publication", "pct": 1.15, "names": [{"name": "Saregama India Ltd", "symbol": "SAREGAMA", "pct": 1.15}]}, {"sector": "Metals & Mining", "pct": 0.81, "names": [{"name": "Hindustan Zinc Ltd", "symbol": "HINDZINC", "pct": 0.81}]}, {"sector": "Diversified", "pct": 0.71, "names": [{"name": "3M India Ltd", "symbol": "3MINDIA", "pct": 0.71}]}, {"sector": "Construction", "pct": 0.57, "names": [{"name": "Power Mech Projects Ltd", "symbol": "POWERMECH", "pct": 0.57}]}, {"sector": "Textiles", "pct": 0.26, "names": [{"name": "Pearl Global Industries Ltd", "symbol": "PGIL", "pct": 0.26}]}], "rotation": {"dates": ["2024-09", "2025-03", "2025-09", "2026-03", "2026-05"], "sectors": ["Financial Services", "Healthcare", "Consumer Services", "Capital Goods", "Automobile and Auto Components", "Information Technology", "Consumer Durables", "Fast Moving Consumer Goods", "Services", "Unclassified", "Other"], "matrix": [[16.7, 18.5, 19.5, 20.2, 18.5], [14.8, 11.4, 10.8, 9.8, 8.8], [11.0, 10.1, 10.2, 10.8, 10.0], [11.1, 6.2, 7.8, 7.3, 8.2], [3.4, 4.8, 8.7, 9.8, 8.7], [5.8, 8.9, 4.6, 5.0, 4.9], [4.8, 5.2, 4.1, 4.2, 4.1], [2.9, 4.1, 4.3, 4.9, 5.8], [1.8, 3.8, 4.9, 1.3, 2.3], [13.3, 13.6, 9.6, 9.7, 13.8], [14.5, 13.4, 15.3, 17.0, 14.9]]}, "conc_ts": [{"ym": "2024-09", "top10": 26.3, "n": 79}, {"ym": "2025-03", "top10": 33.4, "n": 70}, {"ym": "2025-09", "top10": 32.5, "n": 75}, {"ym": "2026-03", "top10": 33.7, "n": 71}, {"ym": "2026-05", "top10": 32.1, "n": 73}]}}